passgen.py
passgen-1.1.1.dist-info/LICENSE
passgen-1.1.1.dist-info/METADATA
passgen-1.1.1.dist-info/WHEEL
passgen-1.1.1.dist-info/entry_points.txt
passgen-1.1.1.dist-info/top_level.txt
passgen-1.1.1.dist-info/RECORD
