Metadata-Version: 1.1
Name: passgen
Version: 1.1.1
Summary: Random password generator
Home-page: https://github.com/soslan/passgen
Author: Soslan Khubulov
Author-email: soslanx@gmail.com
License: MIT
Keywords: password random
Platform: UNKNOWN
Classifier: Development Status :: 5 - Production/Stable
Classifier: Programming Language :: Python :: 2.7
Classifier: Programming Language :: Python :: 3
Classifier: Environment :: Console
Classifier: Intended Audience :: End Users/Desktop
Classifier: Intended Audience :: Developers
Classifier: License :: OSI Approved :: MIT License
Classifier: Natural Language :: English
Classifier: Topic :: Utilities
